apillava/__init__.py
apillava/constants.py
apillava/conversation.py
apillava/hook.py
apillava/mm_utils.py
apillava/utils.py
apillava/eval/eval_gpt_review.py
apillava/eval/eval_gpt_review_bench.py
apillava/eval/eval_gpt_review_visual.py
apillava/eval/eval_pope.py
apillava/eval/eval_science_qa.py
apillava/eval/eval_science_qa_gpt4.py
apillava/eval/eval_science_qa_gpt4_requery.py
apillava/eval/eval_textvqa.py
apillava/eval/generate_webpage_data_from_table.py
apillava/eval/m4c_evaluator.py
apillava/eval/model_qa.py
apillava/eval/model_vqa.py
apillava/eval/model_vqa_loader.py
apillava/eval/model_vqa_mmbench.py
apillava/eval/model_vqa_qbench.py
apillava/eval/model_vqa_science.py
apillava/eval/qa_baseline_gpt35.py
apillava/eval/run_llava.py
apillava/eval/summarize_gpt_review.py
apillava/model/__init__.py
apillava/model/apply_delta.py
apillava/model/builder.py
apillava/model/consolidate.py
apillava/model/llava_arch.py
apillava/model/make_delta.py
apillava/model/utils.py
apillava/model/language_model/llava_llama.py
apillava/model/language_model/llava_mpt.py
apillava/model/language_model/mpt/adapt_tokenizer.py
apillava/model/language_model/mpt/attention.py
apillava/model/language_model/mpt/blocks.py
apillava/model/language_model/mpt/configuration_mpt.py
apillava/model/language_model/mpt/custom_embedding.py
apillava/model/language_model/mpt/flash_attn_triton.py
apillava/model/language_model/mpt/hf_prefixlm_converter.py
apillava/model/language_model/mpt/meta_init_context.py
apillava/model/language_model/mpt/modeling_mpt.py
apillava/model/language_model/mpt/norm.py
apillava/model/language_model/mpt/param_init_fns.py
apillava/model/multimodal_encoder/builder.py
apillava/model/multimodal_encoder/clip_encoder.py
apillava/model/multimodal_projector/builder.py
apillava/serve/__init__.py
apillava/serve/cli.py
apillava/serve/controller.py
apillava/serve/gradio_web_server.py
apillava/serve/model_worker.py
apillava/serve/register_worker.py
apillava/serve/test_message.py
apillava-0.1.0.dist-info/LICENSE
apillava-0.1.0.dist-info/METADATA
apillava-0.1.0.dist-info/WHEEL
apillava-0.1.0.dist-info/top_level.txt
apillava-0.1.0.dist-info/RECORD
