Metadata-Version: 2.1
Name: apillava
Version: 0.1.0
Summary: Modified llava 1.1.3 for apiprompting.
Classifier: Programming Language :: Python :: 3
Classifier: License :: OSI Approved :: Apache Software License
Requires-Python: >=3.8
License-File: LICENSE
Requires-Dist: torch ==2.0.1
Requires-Dist: torchvision ==0.15.2
Requires-Dist: transformers ==4.31.0
Requires-Dist: tokenizers <0.14,>=0.12.1
Requires-Dist: sentencepiece ==0.1.99
Requires-Dist: shortuuid
Requires-Dist: accelerate ==0.21.0
Requires-Dist: peft ==0.4.0
Requires-Dist: bitsandbytes ==0.41.0
Requires-Dist: pydantic <2,>=1
Requires-Dist: markdown2[all]
Requires-Dist: numpy ==1.24.0
Requires-Dist: scikit-learn ==1.2.2
Requires-Dist: gradio ==3.35.2
Requires-Dist: gradio-client ==0.2.9
Requires-Dist: requests
Requires-Dist: httpx ==0.24.0
Requires-Dist: uvicorn
Requires-Dist: fastapi
Requires-Dist: einops ==0.6.1
Requires-Dist: einops-exts ==0.0.4
Requires-Dist: timm ==0.6.13
Provides-Extra: train
Requires-Dist: deepspeed ==0.9.5 ; extra == 'train'
Requires-Dist: ninja ; extra == 'train'
Requires-Dist: wandb ; extra == 'train'
